{
  "country": "New Zealand",
  "code": "NZ",
  "continent": "Oceania",
  "appellations": [
    {
      "name": "New Zealand Wine",
      "type": "National"
    }
  ],
  "regions": [
    {
      "name": "Marlborough",
      "appellations": [
        {
          "name": "Marlborough Wine",
          "type": "GI"
        },
        {
          "name": "Marlborough",
          "type": "GI"
        }
      ],
      "subRegions": [
        {
          "name": "Wairau Valley"
        },
        {
          "name": "Awatere Valley"
        },
        {
          "name": "Southern Valleys"
        }
      ]
    },
    {
      "name": "Hawke's Bay",
      "subRegions": [
        {
          "name": "Gimblett Gravels"
        },
        {
          "name": "Bridge Pa Triangle"
        }
      ],
      "appellations": [
        {
          "name": "Hawke's Bay",
          "type": "GI"
        }
      ]
    },
    {
      "name": "Central Otago",
      "appellations": [
        {
          "name": "Central Otago Wine",
          "type": "GI"
        },
        {
          "name": "Central Otago",
          "type": "GI"
        }
      ],
      "subRegions": [
        {
          "name": "Bannockburn"
        },
        {
          "name": "Cromwell Basin"
        },
        {
          "name": "Gibbston"
        },
        {
          "name": "Wanaka"
        },
        {
          "name": "Bendigo"
        },
        {
          "name": "Alexandra"
        }
      ]
    },
    {
      "name": "Canterbury",
      "subRegions": [
        {
          "name": "Waipara Valley"
        },
        {
          "name": "Christchurch Plains"
        }
      ],
      "appellations": [
        {
          "name": "Canterbury",
          "type": "GI"
        }
      ]
    },
    {
      "name": "Wairarapa",
      "subRegions": [
        {
          "name": "Martinborough",
          "appellations": [
            {
              "name": "Martinborough",
              "type": "GI"
            }
          ]
        }
      ]
    },
    {
      "name": "Nelson",
      "subRegions": [
        {
          "name": "Waimea Plains"
        },
        {
          "name": "Moutere Hills"
        }
      ],
      "appellations": [
        {
          "name": "Nelson",
          "type": "GI"
        }
      ]
    },
    {
      "name": "Waitaki Valley",
      "subRegions": [
        {
          "name": "Waitaki Valley",
          "appellations": [
            {
              "name": "Waitaki Valley",
              "type": "GI"
            }
          ]
        }
      ]
    },
    {
      "name": "Gisborne",
      "subRegions": [
        {
          "name": "Gisborne",
          "appellations": [
            {
              "name": "Gisborne",
              "type": "GI"
            }
          ]
        }
      ]
    },
    {
      "name": "Auckland",
      "subRegions": [
        {
          "name": "Waiheke Island"
        },
        {
          "name": "Henderson"
        },
        {
          "name": "Matakana"
        }
      ],
      "appellations": [
        {
          "name": "Auckland",
          "type": "GI"
        }
      ]
    },
    {
      "name": "Northland",
      "subRegions": [
        {
          "name": "Northland",
          "appellations": [
            {
              "name": "Northland",
              "type": "GI"
            }
          ]
        }
      ]
    }
  ]
}
